interzoid_address_match_key/__init__.py
interzoid_address_match_key/address_match_key.py
interzoid_address_match_key-1.0.0.dist-info/METADATA
interzoid_address_match_key-1.0.0.dist-info/WHEEL
interzoid_address_match_key-1.0.0.dist-info/licenses/LICENSE
interzoid_address_match_key-1.0.0.dist-info/RECORD
