Metadata-Version: 2.1
Name: interzoid_address_match_key
Version: 1.0.0
Summary: Provides an AI-based street address similarity key used to match inconsistent address data.
Project-URL: Homepage, https://www.interzoid.com/apis/street-address-matching
Author-email: Interzoid <support@interzoid.com>
License-File: LICENSE
Classifier: License :: OSI Approved :: MIT License
Classifier: Operating System :: OS Independent
Classifier: Programming Language :: Python :: 3
Classifier: Topic :: Database
Classifier: Topic :: Scientific/Engineering :: Artificial Intelligence
Requires-Python: >=3.7
